Workbook

Sheet Resumo
A1: Resumo por classe
A2: Valores com BDI, calculados a partir da aba "Curva ABC".
A4: Classe | B4: Linhas | C4: Valor (R$) | D4: % | E4: Δ BDI (R$)
A5: A | B5: =COUNTIF('Curva ABC'!$A$5:$A$81,A5) -> 19 | C5: =SUMIF('Curva ABC'!$A$5:$A$81,A5,'Curva ABC'!$G$5:$G$81) -> 631986.26 | D5: =C5/$C$8 -> 0.81157144 | E5: =SUMIF('Curva ABC'!$A$5:$A$81,A5,'Curva ABC'!$K$5:$K$81) -> -23632.54
A6: B | B6: =COUNTIF('Curva ABC'!$A$5:$A$81,A6) -> 20 | C6: =SUMIF('Curva ABC'!$A$5:$A$81,A6,'Curva ABC'!$G$5:$G$81) -> 109648.24 | D6: =C6/$C$8 -> 0.14080588 | E6: =SUMIF('Curva ABC'!$A$5:$A$81,A6,'Curva ABC'!$K$5:$K$81) -> -904.83
A7: C | B7: =COUNTIF('Curva ABC'!$A$5:$A$81,A7) -> 38 | C7: =SUMIF('Curva ABC'!$A$5:$A$81,A7,'Curva ABC'!$G$5:$G$81) -> 37084.7 | D7: =C7/$C$8 -> 0.047622686 | E7: =SUMIF('Curva ABC'!$A$5:$A$81,A7,'Curva ABC'!$K$5:$K$81) -> -418.59
A8: Total | B8: =SUM(B5:B7) -> 77 | C8: =SUM(C5:C7) -> 778719.2 | D8: =SUM(D5:D7) -> 1 | E8: =SUM(E5:E7) -> -24955.96
A10: Valores de controle (tabela do usuário): A 631.986,26 · B 109.648,24 · C 37.084,70 · Total 778.719,20 · Δ BDI −24.955,96.
A12: Valor por fonte do preço
A13: Fonte | B13: Linhas | C13: Valor (R$) | D13: %
A14: SINAPI | B14: =COUNTIF('Curva ABC'!$M$5:$M$81,A14) -> 36 | C14: =SUMIF('Curva ABC'!$M$5:$M$81,A14,'Curva ABC'!$G$5:$G$81) -> 79608.58 | D14: =C14/$C$22 -> 0.10223015
A15: SINAPI sem custo | B15: =COUNTIF('Curva ABC'!$M$5:$M$81,A15) -> 1 | C15: =SUMIF('Curva ABC'!$M$5:$M$81,A15,'Curva ABC'!$G$5:$G$81) -> 47892 | D15: =C15/$C$22 -> 0.061500988
A16: SEDOP | B16: =COUNTIF('Curva ABC'!$M$5:$M$81,A16) -> 2 | C16: =SUMIF('Curva ABC'!$M$5:$M$81,A16,'Curva ABC'!$G$5:$G$81) -> 9093.33 | D16: =C16/$C$22 -> 0.01167729
A17: ORSE | B17: =COUNTIF('Curva ABC'!$M$5:$M$81,A17) -> 2 | C17: =SUMIF('Curva ABC'!$M$5:$M$81,A17,'Curva ABC'!$G$5:$G$81) -> 338.55 | D17: =C17/$C$22 -> 0.00043475235
A18: EMBASA | B18: =COUNTIF('Curva ABC'!$M$5:$M$81,A18) -> 1 | C18: =SUMIF('Curva ABC'!$M$5:$M$81,A18,'Curva ABC'!$G$5:$G$81) -> 25370.35 | D18: =C18/$C$22 -> 0.032579587
A19: Cotação Biomais | B19: =COUNTIF('Curva ABC'!$M$5:$M$81,A19) -> 19 | C19: =SUMIF('Curva ABC'!$M$5:$M$81,A19,'Curva ABC'!$G$5:$G$81) -> 493404.28 | D19: =C19/$C$22 -> 0.63361001
A20: Cotação | B20: =COUNTIF('Curva ABC'!$M$5:$M$81,A20) -> 11 | C20: =SUMIF('Curva ABC'!$M$5:$M$81,A20,'Curva ABC'!$G$5:$G$81) -> 108797.46 | D20: =C20/$C$22 -> 0.13971334
A21: Composição própria | B21: =COUNTIF('Curva ABC'!$M$5:$M$81,A21) -> 5 | C21: =SUMIF('Curva ABC'!$M$5:$M$81,A21,'Curva ABC'!$G$5:$G$81) -> 14214.65 | D21: =C21/$C$22 -> 0.018253884
A22: Total | B22: =SUM(B14:B21) -> 77 | C22: =SUM(C14:C21) -> 778719.2 | D22: =SUM(D14:D21) -> 1
A23: Linhas agrupadas contam uma vez (ex.: 12.4.1 + 12.4.2). "SINAPI" inclui o 10.11, composição própria com o custo do SINAPI 94493.

Sheet Curva ABC
A1: Curva ABC corrigida: itens de engenharia mecânica (aba PLANILHA ORÇAMENTÁRIA)
A2: Obra: ETE do Hospital Barros Barreto (Belém/PA) · Orçamentista: Sanigy · Data-base 06/2025 · SINAPI-PA desonerado · Escopo: 80 itens mecânicos, agrupados em 77 linhas
A4: Classe | B4: # | C4: Item | D4: Linha | E4: Descrição | F4: Qtd | G4: R$ c/ BDI | H4: % do total | I4: % acum. | J4: BDI | K4: Δ BDI (R$) | L4: Verificar (bloco) e status | M4: Fonte do preço | N4: Código / evidência | O4: Situação do preço na fonte
A5: A | B5: 1 | C5: 12.4.1 + 12.4.2 | D5: 255 e 256 | E5: Decantador secundário 4,00 × 4,10 m + frete | F5: 2 + 2 | G5: 215671.4 | H5: =G5/$G$82 -> 0.27695657 | I5: =SUM($G$5:G5)/$G$82 -> 0.27695657 | J5: S → A | K5: -19178.68 | L5: Bloco F: proposta única; linha sem especificação (lamelas, internos); montagem do decantador não consta; BDI → aquisição (equipamento −R$ 17.932,38; frete −R$ 1.246,30); pedir cotação de transporte (AET) | M5: Cotação Biomais | N5: — | O5: Proposta única de 24/07/2025 (só a pág. 4, image36.png), sem CNPJ, validade ou especificação
A6: A | B6: 2 | C6: 6.1 + 6.2 | D6: 69 e 70 | E6: Guindaste 75 t (horas produtivas + improdutivas) | F6: 240 h + 480 h | G6: 47892 | H6: =G6/$G$82 -> 0.061500988 | I6: =SUM($G$5:G6)/$G$82 -> 0.33845756 | J6: S | L6: Bloco B: NÃO OK; sem custo oficial (hora = combustível + operador, sem a máquina); 720 h sem plano de içamento; falta mobilização do guindaste | M6: SINAPI sem custo | N6: 102850 / 102851 | O6: Código "sem custo" desde 11/2021; a planilha recompôs a hora só com materiais (102849) + operador (88296)
A7: A | B7: 3 | C7: 12.1.3 | D7: 236 | E7: Revestimento e reforço interno (UASB) | F7: 2 | G7: 33609.38 | H7: =G7/$G$82 -> 0.043159819 | I7: =SUM($G$5:G7)/$G$82 -> 0.38161738 | J7: S | L7: Bloco F: unidade nova ou existente? base em m² | M7: Cotação Biomais | N7: — | O7: Proposta única de 24/07/2025 (só a pág. 4, image36.png), sem CNPJ, validade ou especificação
A8: A | B8: 4 | C8: 10.4 | D8: 208 | E8: Difusor 250 mm | F8: 140 | G8: 30354.8 | H8: =G8/$G$82 -> 0.038980418 | I8: =SUM($G$5:G8)/$G$82 -> 0.4205978 | J8: A | L8: Bloco E: preço OK; 140 fecha com a rede | M8: Cotação | N8: Print de loja + mão de obra | O8: Difusor R$ 161,20 (cotação); mão de obra ≈ R$ 25,58, provável 0,5 h de 88267 + 0,5 h de 88248 (a confirmar na CPU)
A9: A | B9: 5 | C9: 12.1.6 | D9: 239 | E9: Montagem do sistema (UASB) | F9: 2 | G9: 29576.26 | H9: =G9/$G$82 -> 0.037980648 | I9: =SUM($G$5:G9)/$G$82 -> 0.45857845 | J9: S | L9: Bloco F: pode repetir o revestimento | M9: Cotação Biomais | N9: — | O9: Proposta única de 24/07/2025 (só a pág. 4, image36.png), sem CNPJ, validade ou especificação
A10: A | B10: 6 | C10: 12.2.1 | D10: 242 | E10: Revestimento e reforço interno (FBAS) | F10: 2 | G10: 29576.26 | H10: =G10/$G$82 -> 0.037980648 | I10: =SUM($G$5:G10)/$G$82 -> 0.49655909 | J10: S | L10: Bloco F: base de cálculo vs 12.1.3 | M10: Cotação Biomais | N10: — | O10: Proposta única de 24/07/2025 (só a pág. 4, image36.png), sem CNPJ, validade ou especificação
A11: A | B11: 7 | C11: 12.1.1 | D11: 234 | E11: Separador trifásico | F11: 2 | G11: 25886.62 | H11: =G11/$G$82 -> 0.03324256 | I11: =SUM($G$5:G11)/$G$82 -> 0.52980165 | J11: S → A | K11: -2301.98 | L11: Bloco F: escopo da proposta; BDI → aquisição | M11: Cotação Biomais | N11: — | O11: Proposta única de 24/07/2025 (só a pág. 4, image36.png), sem CNPJ, validade ou especificação
A12: A | B12: 8 | C12: 1.13 | D12: 28 | E12: Comissionamento da ETE (EMBASA) | F12: 1 | G12: 25370.35 | H12: =G12/$G$82 -> 0.032579587 | I12: =SUM($G$5:G12)/$G$82 -> 0.56238124 | J12: S | L12: Bloco A: NÃO VERIFICÁVEL; EMBASA/BA; sobreposição com guindaste | M12: EMBASA | N12: 41.05.01 | O12: Tabela EMBASA/BA não disponível; mesmo código na planilha do projetista (R$ 38.386,51)
A13: A | B13: 9 | C13: 10.3 | D13: 207 | E13: Soprador radial duplo estágio | F13: 2 | G13: 24987.56 | H13: =G13/$G$82 -> 0.032088024 | I13: =SUM($G$5:G13)/$G$82 -> 0.59446926 | J13: A | L13: Bloco E: NÃO VERIFICÁVEL; especificação em 3 versões | M13: Cotação | N13: Print Policomp JQT-7500 (image7.png) | O13: Especificação em 3 versões (item, CPU e print)
A14: A | B14: 10 | C14: 12.1.2 | D14: 235 | E14: Defletor em PRFV | F14: 2 | G14: 24198.74 | H14: =G14/$G$82 -> 0.031075052 | I14: =SUM($G$5:G14)/$G$82 -> 0.62554432 | J14: S → A | K14: -2151.88 | L14: Bloco F: escopo da proposta; BDI → aquisição | M14: Cotação Biomais | N14: — | O14: Proposta única de 24/07/2025 (só a pág. 4, image36.png), sem CNPJ, validade ou especificação
A15: A | B15: 11 | C15: 12.2.4 | D15: 245 | E15: Montagem do sistema (FBAS) | F15: 2 | G15: 24198.74 | H15: =G15/$G$82 -> 0.031075052 | I15: =SUM($G$5:G15)/$G$82 -> 0.65661937 | J15: S | L15: Bloco F: pode repetir o revestimento | M15: Cotação Biomais | N15: — | O15: Proposta única de 24/07/2025 (só a pág. 4, image36.png), sem CNPJ, validade ou especificação
A16: A | B16: 12 | C16: 10.8 | D16: 212 | E16: Pall ring 2" | F16: 15 m³ | G16: 21270.15 | H16: =G16/$G$82 -> 0.027314275 | I16: =SUM($G$5:G16)/$G$82 -> 0.68393364 | J16: A | L16: Bloco E: OK com ressalva; 2" × 3"; conferir volume | M16: Cotação | N16: Print de loja | O16: R$ 1.180,00/m³ (cotação "2"")
A17: A | B17: 13 | C17: 12.1.5 | D17: 238 | E17: Substituição do acesso lateral e superior (UASB) | F17: 2 | G17: 17476.88 | H17: =G17/$G$82 -> 0.022443109 | I17: =SUM($G$5:G17)/$G$82 -> 0.70637675 | J17: S | L17: Bloco F: reforma de unidade existente? | M17: Cotação Biomais | N17: — | O17: Proposta única de 24/07/2025 (só a pág. 4, image36.png), sem CNPJ, validade ou especificação
A18: A | B18: 14 | C18: 12.1.4 | D18: 237 | E18: Pintura com gelcoat (UASB) | F18: 2 | G18: 16132.5 | H18: =G18/$G$82 -> 0.02071671 | I18: =SUM($G$5:G18)/$G$82 -> 0.72709346 | J18: S | L18: Bloco F: escopo da proposta | M18: Cotação Biomais | N18: — | O18: Proposta única de 24/07/2025 (só a pág. 4, image36.png), sem CNPJ, validade ou especificação
A19: A | B19: 15 | C19: 12.3.2 | D19: 249 | E19: Revestimento e reforço interno (tanque de contato) | F19: 2 | G19: 16132.5 | H19: =G19/$G$82 -> 0.02071671 | I19: =SUM($G$5:G19)/$G$82 -> 0.74781017 | J19: S | L19: Bloco F: base de cálculo | M19: Cotação Biomais | N19: — | O19: Proposta única de 24/07/2025 (só a pág. 4, image36.png), sem CNPJ, validade ou especificação
A20: A | B20: 16 | C20: 12.3.5 | D20: 252 | E20: Montagem do sistema (tanque de contato) | F20: 2 | G20: 13443.74 | H20: =G20/$G$82 -> 0.017263912 | I20: =SUM($G$5:G20)/$G$82 -> 0.76507409 | J20: S | L20: Bloco F: pode repetir o revestimento | M20: Cotação Biomais | N20: — | O20: Proposta única de 24/07/2025 (só a pág. 4, image36.png), sem CNPJ, validade ou especificação
A21: A | B21: 17 | C21: 8.2.14 | D21: 108 | E21: Tê de redução 75 × 50 | F21: 140 | G21: 13400.8 | H21: =G21/$G$82 -> 0.017208771 | I21: =SUM($G$5:G21)/$G$82 -> 0.78228286 | J21: S | L21: Bloco C: 140 = difusores; sem tubo DN 50; ≈ 2,6 saídas/m | M21: SINAPI | N21: 94698 | O21: Igual à tabela SINAPI-PA 06/2025 ao centavo
A22: A | B22: 18 | C22: 10.7 | D22: 211 | E22: Motobomba submersível Brava E30 | F22: 2 | G22: 13396.96 | H22: =G22/$G$82 -> 0.017203839 | I22: =SUM($G$5:G22)/$G$82 -> 0.7994867 | J22: A | L22: Bloco E: preço OK; função e ponto de operação | M22: Cotação | N22: Print de loja | O22: Motobomba Brava E30, R$ 5.679,24
A23: A | B23: 19 | C23: 12.2.2 | D23: 243 | E23: Pintura com gelcoat (FBAS) | F23: 2 | G23: 9410.62 | H23: =G23/$G$82 -> 0.012084741 | I23: =SUM($G$5:G23)/$G$82 -> 0.81157144 | J23: S | L23: Bloco F: escopo da proposta | M23: Cotação Biomais | N23: — | O23: Proposta única de 24/07/2025 (só a pág. 4, image36.png), sem CNPJ, validade ou especificação
A24: B | B24: 20 | C24: 12.2.3 | D24: 244 | E24: Substituição do acesso superior (FBAS) | F24: 2 | G24: 8738.44 | H24: =G24/$G$82 -> 0.011221555 | I24: =SUM($G$5:G24)/$G$82 -> 0.82279299 | J24: S | L24: Bloco F: escopo da proposta | M24: Cotação Biomais | N24: — | O24: Proposta única de 24/07/2025 (só a pág. 4, image36.png), sem CNPJ, validade ou especificação
A25: B | B25: 21 | C25: 12.3.4 | D25: 251 | E25: Substituição do acesso superior (tanque de contato) | F25: 2 | G25: 8738.44 | H25: =G25/$G$82 -> 0.011221555 | I25: =SUM($G$5:G25)/$G$82 -> 0.83401455 | J25: S | L25: Bloco F: escopo da proposta | M25: Cotação Biomais | N25: — | O25: Proposta única de 24/07/2025 (só a pág. 4, image36.png), sem CNPJ, validade ou especificação
A26: B | B26: 22 | C26: 12.3.1 | D26: 248 | E26: Kit chincana | F26: 2 | G26: 8263.86 | H26: =G26/$G$82 -> 0.010612118 | I26: =SUM($G$5:G26)/$G$82 -> 0.84462666 | J26: S → A | K26: -734.88 | L26: Bloco F: fornecimento sem montagem; BDI → aquisição | M26: Cotação Biomais | N26: — | O26: Proposta única de 24/07/2025 (só a pág. 4, image36.png), sem CNPJ, validade ou especificação
A27: B | B27: 23 | C27: 1.16 | D27: 31 | E27: Comissionamento do combate a incêndio | F27: 1 | G27: 8043.13 | H27: =G27/$G$82 -> 0.010328665 | I27: =SUM($G$5:G27)/$G$82 -> 0.85495533 | J27: S | L27: Bloco A: NÃO OK; excluir ou reduzir | M27: Composição própria | N27: Composição 29 (projetista) | O27: 40 h eng. júnior 90777 + 40 h encanador 88267 + 20 h auxiliar 88248 (SINAPI)
A28: B | B28: 24 | C28: 10.10 | D28: 214 | E28: Registro de gaveta 4" | F28: 3 | G28: 7719.81 | H28: =G28/$G$82 -> 0.0099134707 | I28: =SUM($G$5:G28)/$G$82 -> 0.8648688 | J28: S | L28: Bloco E: SEDOP, NÃO VERIFICÁVEL; flange ou rosca? | M28: SEDOP | N28: 180801 | O28: "Registro de gaveta 4" - bruto"; tabela SEDOP não disponível
A29: B | B29: 25 | C29: 8.2.6 | D29: 100 | E29: Tubo PVC DN 110 | F29: 39 m | G29: 6998.55 | H29: =G29/$G$82 -> 0.0089872575 | I29: =SUM($G$5:G29)/$G$82 -> 0.87385606 | J29: S | L29: Bloco C: preço OK; temperatura do ar × PVC | M29: SINAPI | N29: 94655 | O29: Igual à tabela SINAPI-PA 06/2025 ao centavo
A30: B | B30: 26 | C30: 10.1 | D30: 205 | E30: Calha Parshall 6" | F30: 1 | G30: 6902.11 | H30: =G30/$G$82 -> 0.0088634132 | I30: =SUM($G$5:G30)/$G$82 -> 0.88271947 | J30: A | L30: Bloco E: OK com ressalva; cotação inclui caixas | M30: Cotação | N30: Print Bakof (image5.png) | O30: R$ 5.883,02, com caixas de entrada e saída
A31: B | B31: 27 | C31: 8.3.1 | D31: 122 | E31: Tubo aço galvanizado DN 80 | F31: 34 m | G31: 6742.54 | H31: =G31/$G$82 -> 0.0086584998 | I31: =SUM($G$5:G31)/$G$82 -> 0.89137797 | J31: S | L31: Bloco D: NÃO OK; conexões são 2½" | M31: SINAPI | N31: 94464 | O31: Igual à tabela SINAPI-PA 06/2025 ao centavo
A32: B | B32: 28 | C32: 8.2.23 | D32: 117 | E32: Adaptador com flanges DN 110 × 4" | F32: 14 | G32: 6191.78 | H32: =G32/$G$82 -> 0.0079512358 | I32: =SUM($G$5:G32)/$G$82 -> 0.89932921 | J32: S | L32: Bloco C: 14 = 2×(3+4) coerente; tipo de conexão | M32: SINAPI | N32: 94715 | O32: Igual à tabela SINAPI-PA 06/2025 ao centavo
A33: B | B33: 29 | C33: 8.2.19 | D33: 113 | E33: União PVC DN 110 (Tigre) | F33: 8 | G33: 4871.44 | H33: =G33/$G$82 -> 0.0062557081 | I33: =SUM($G$5:G33)/$G$82 -> 0.90558491 | J33: S | L33: Bloco C: por que 8? marca Tigre | M33: Composição própria | N33: Composição 4 (projetista) | O33: Insumo SINAPI 9908 (união 110 mm) + mão de obra SINAPI; descrição com marca "Tigre"
A34: B | B34: 30 | C34: 12.3.3 | D34: 250 | E34: Pintura com gelcoat (tanque de contato) | F34: 2 | G34: 4705.3 | H34: =G34/$G$82 -> 0.0060423578 | I34: =SUM($G$5:G34)/$G$82 -> 0.91162727 | J34: S | L34: Bloco F: escopo da proposta | M34: Cotação Biomais | N34: — | O34: Proposta única de 24/07/2025 (só a pág. 4, image36.png), sem CNPJ, validade ou especificação
A35: B | B35: 31 | C35: 10.5 | D35: 209 | E35: Filtro de entrada | F35: 2 | G35: 4132.98 | H35: =G35/$G$82 -> 0.0053074073 | I35: =SUM($G$5:G35)/$G$82 -> 0.91693468 | J35: A | L35: Bloco E: NÃO OK; filtro 2" × soprador | M35: Cotação | N35: Print de loja | O35: Filtro de 2" para até 5 m³/min
A36: B | B36: 32 | C36: 8.2.11 | D36: 105 | E36: Joelho 90° DN 110 | F36: 11 | G36: 4084.19 | H36: =G36/$G$82 -> 0.0052447532 | I36: =SUM($G$5:G36)/$G$82 -> 0.92217943 | J36: S | L36: Bloco C: conferir no isométrico | M36: SINAPI | N36: 94686 | O36: Igual à tabela SINAPI-PA 06/2025 ao centavo
A37: B | B37: 33 | C37: 12.3.6 | D37: 253 | E37: Frete do conjunto tanque de contato | F37: 2 | G37: 3822.3 | H37: =G37/$G$82 -> 0.0049084445 | I37: =SUM($G$5:G37)/$G$82 -> 0.92708788 | J37: S → A | K37: -169.95 | L37: Bloco F: NÃO OK; qtd 2 × proposta 1 (−R$ 1.911,15, à parte); BDI → aquisição | M37: Cotação Biomais | N37: — | O37: Proposta única de 24/07/2025 (só a pág. 4, image36.png), sem CNPJ, validade ou especificação
A38: B | B38: 34 | C38: 8.2.4 | D38: 98 | E38: Tubo PVC DN 75 | F38: 53 m | G38: 3818.65 | H38: =G38/$G$82 -> 0.0049037573 | I38: =SUM($G$5:G38)/$G$82 -> 0.93199163 | J38: S | L38: Bloco C: comprimento × planta | M38: SINAPI | N38: 89451 | O38: Igual à tabela SINAPI-PA 06/2025 ao centavo
A39: B | B39: 35 | C39: 8.2.10 | D39: 104 | E39: Joelho 90° DN 75 | F39: 24 | G39: 3658.08 | H39: =G39/$G$82 -> 0.0046975598 | I39: =SUM($G$5:G39)/$G$82 -> 0.93668919 | J39: S | L39: Bloco C: conferir no isométrico | M39: SINAPI | N39: 89513 | O39: Igual à tabela SINAPI-PA 06/2025 ao centavo
A40: B | B40: 36 | C40: 10.2 | D40: 206 | E40: Bomba dosadora EMEC FCE | F40: 2 | G40: 3299.14 | H40: =G40/$G$82 -> 0.0042366234 | I40: =SUM($G$5:G40)/$G$82 -> 0.94092582 | J40: A | L40: Bloco E: NÃO VERIFICÁVEL; pedir 3 propostas | M40: Cotação | N40: Print de loja | O40: Dosadora EMEC FCE, R$ 1.367,90
A41: B | B41: 37 | C41: 10.16 | D41: 220 | E41: Retenção horizontal 4" | F41: 2 | G41: 3144.44 | H41: =G41/$G$82 -> 0.0040379639 | I41: =SUM($G$5:G41)/$G$82 -> 0.94496378 | J41: S | L41: Bloco E: preço OK; 4 retenções p/ 2 bombas | M41: SINAPI | N41: 99626 | O41: Igual à tabela SINAPI-PA 06/2025 ao centavo
A42: B | B42: 38 | C42: 8.2.3 | D42: 97 | E42: Tubo PVC DN 60 | F42: 67 m | G42: 2957.38 | H42: =G42/$G$82 -> 0.0037977489 | I42: =SUM($G$5:G42)/$G$82 -> 0.94876153 | J42: S | L42: Bloco C: 7 tês × 21 registros DN 60 | M42: SINAPI | N42: 89450 | O42: Igual à tabela SINAPI-PA 06/2025 ao centavo
A43: B | B43: 39 | C43: 10.11 + 10.13 | D43: 215 e 217 | E43: Registro de esfera DN 60 (mesmo código SINAPI 94493) | F43: 8 + 13 | G43: 2815.68 | H43: =G43/$G$82 -> 0.0036157835 | I43: =SUM($G$5:G43)/$G$82 -> 0.95237731 | J43: S | L43: Bloco E: NÃO OK; duplicidade; são 21 no projeto? (−R$ 1.072,64 se 8 sobrarem) | M43: SINAPI | N43: 94493 | O43: 10.13 = SINAPI 94493; 10.11 = composição própria "COMPOSIÇÃO 8" com o custo do 94493. Igual à tabela ao centavo
A44: C | B44: 40 | C44: 8.2.16 | D44: 110 | E44: Tê PVC DN 75 | F44: 22 | G44: 2742.08 | H44: =G44/$G$82 -> 0.0035212693 | I44: =SUM($G$5:G44)/$G$82 -> 0.95589858 | J44: S | L44: Bloco C: conferir no isométrico | M44: SINAPI | N44: 94697 | O44: Igual à tabela SINAPI-PA 06/2025 ao centavo
A45: C | B45: 41 | C45: 8.3.9 | D45: 130 | E45: União galvanizada 2½" | F45: 10 | G45: 2719.5 | H45: =G45/$G$82 -> 0.003492273 | I45: =SUM($G$5:G45)/$G$82 -> 0.95939086 | J45: S | L45: Bloco D: coerente com 20 niples | M45: SINAPI | N45: 92890 | O45: Igual à tabela SINAPI-PA 06/2025 ao centavo
A46: C | B46: 42 | C46: 8.2.25 | D46: 119 | E46: Bucha de redução 50 × 25 | F46: 140 | G46: 2402.4 | H46: =G46/$G$82 -> 0.0030850658 | I46: =SUM($G$5:G46)/$G$82 -> 0.96247592 | J46: S | L46: Bloco C: = difusores | M46: SINAPI | N46: 103999 | O46: Igual à tabela SINAPI-PA 06/2025 ao centavo
A47: C | B47: 43 | C47: 8.2.13 | D47: 107 | E47: Luva com bucha de latão 25 × ¾" | F47: 140 | G47: 2377.2 | H47: =G47/$G$82 -> 0.003052705 | I47: =SUM($G$5:G47)/$G$82 -> 0.96552863 | J47: S | L47: Bloco C: = difusores | M47: SINAPI | N47: 89427 | O47: Igual à tabela SINAPI-PA 06/2025 ao centavo
A48: C | B48: 44 | C48: 10.14 | D48: 218 | E48: Válvula de alívio 1¼" | F48: 2 | G48: 2248.88 | H48: =G48/$G$82 -> 0.0028879216 | I48: =SUM($G$5:G48)/$G$82 -> 0.96841655 | J48: A | L48: Bloco E: NÃO VERIFICÁVEL; pressão de abertura | M48: Cotação | N48: Print de loja | O48: Válvula de alívio, R$ 941,05
A49: C | B49: 45 | C49: 10.17 | D49: 221 | E49: Retenção vertical 4" | F49: 2 | G49: 2188.26 | H49: =G49/$G$82 -> 0.0028100758 | I49: =SUM($G$5:G49)/$G$82 -> 0.97122662 | J49: S | L49: Bloco E: confirmar 2 + 2 | M49: SINAPI | N49: 99634 | O49: Igual à tabela SINAPI-PA 06/2025 ao centavo
... A51: C | B51: 47 | C51: 8.3.7 | D51: 128 | E51: Niple galvanizado 2½" | F51: 20 | G51: 1933.4 | H51: =G51/$G$82 -> 0.0024827948 | I51: =SUM($G$5:G51)/$G$82 -> 0.97632168 | J51: S | L51: Bloco D: 2 por união | M51: SINAPI | N51: 94468 | O51: Igual à tabela SINAPI-PA 06/2025 ao centavo
A52: C | B52: 48 | C52: 12.1.7 | D52: 240 | E52: Frete do conjunto UASB | F52: 1 | G52: 1911.15 | H52: =G52/$G$82 -> 0.0024542223 | I52: =SUM($G$5:G52)/$G$82 -> 0.97877591 | J52: S → A | K52: -169.95 | L52: Bloco F: quantidade confere; BDI → aquisição | M52: Cotação Biomais | N52: — | O52: Proposta única de 24/07/2025 (só a pág. 4, image36.png), sem CNPJ, validade ou especificação
A53: C | B53: 49 | C53: 12.2.5 | D53: 246 | E53: Frete do conjunto FBAS | F53: 1 | G53: 1911.15 | H53: =G53/$G$82 -> 0.0024542223 | I53: =SUM($G$5:G53)/$G$82 -> 0.98123013 | J53: S → A | K53: -169.95 | L53: Bloco F: quantidade confere; BDI → aquisição | M53: Cotação Biomais | N53: — | O53: Proposta única de 24/07/2025 (só a pág. 4, image36.png), sem CNPJ, validade ou especificação
A54: C | B54: 50 | C54: 10.15 | D54: 219 | E54: Retenção horizontal 2½" | F54: 2 | G54: 1483.34 | H54: =G54/$G$82 -> 0.0019048458 | I54: =SUM($G$5:G54)/$G$82 -> 0.98313497 | J54: S | L54: Bloco E: OK; uma por soprador | M54: SINAPI | N54: 99624 | O54: Igual à tabela SINAPI-PA 06/2025 ao centavo
A55: C | B55: 51 | C55: 10.9 | D55: 213 | E55: Registro de gaveta 2½" | F55: 2 | G55: 1373.52 | H55: =G55/$G$82 -> 0.0017638194 | I55: =SUM($G$5:G55)/$G$82 -> 0.98489879 | J55: S | L55: Bloco E: SEDOP, NÃO VERIFICÁVEL | M55: SEDOP | N55: 180803 | O55: "Registro de gaveta 2 1/2" - bruto"; tabela SEDOP não disponível
A56: C | B56: 52 | C56: 8.2.26 | D56: 120 | E56: Curva 90° DN 110 | F56: 4 | G56: 1340.4 | H56: =G56/$G$82 -> 0.001721288 | I56: =SUM($G$5:G56)/$G$82 -> 0.98662008 | J56: S | L56: Bloco C: conferir no isométrico | M56: SINAPI | N56: 94687 | O56: Igual à tabela SINAPI-PA 06/2025 ao centavo
A57: C | B57: 53 | C57: 8.2.20 | D57: 114 | E57: Adaptador curto com rosca 25 × ¾" | F57: 140 | G57: 1232 | H57: =G57/$G$82 -> 0.001582085 | I57: =SUM($G$5:G57)/$G$82 -> 0.98820217 | J57: S | L57: Bloco C: = difusores | M57: SINAPI | N57: 89383 | O57: Igual à tabela SINAPI-PA 06/2025 ao centavo
A58: C | B58: 54 | C58: 8.3.2 | D58: 123 | E58: Vara de tubo galvanizado "DN 110" | F58: 1 | G58: 1011.43 | H58: =G58/$G$82 -> 0.0012988379 | I58: =SUM($G$5:G58)/$G$82 -> 0.989501 | J58: A | L58: Bloco D: onde entra? sem conexão de 4" | M58: Cotação | N58: Cotação (projetista) | O58: ≈ R$ 145/m, contra R$ 194 a R$ 209/m dos SINAPI de 4"
A59: C | B59: 55 | C59: 8.2.17 | D59: 111 | E59: Tê PVC DN 110 | F59: 3 | G59: 986.01 | H59: =G59/$G$82 -> 0.0012661945 | I59: =SUM($G$5:G59)/$G$82 -> 0.9907672 | J59: S | L59: Bloco C: conferir no isométrico | M59: SINAPI | N59: 94701 | O59: Igual à tabela SINAPI-PA 06/2025 ao centavo
A60: C | B60: 56 | C60: 8.3.5 | D60: 126 | E60: Cotovelo 90° galvanizado 2½" | F60: 6 | G60: 948.42 | H60: =G60/$G$82 -> 0.001217923 | I60: =SUM($G$5:G60)/$G$82 -> 0.99198512 | J60: S | L60: Bloco D: conferir no isométrico | M60: SINAPI | N60: 94473 | O60: Igual à tabela SINAPI-PA 06/2025 ao centavo
A61: C | B61: 57 | C61: 8.3.8 | D61: 129 | E61: Tê de redução 2½ × 1¼" | F61: 4 | G61: 947.92 | H61: =G61/$G$82 -> 0.0012172809 | I61: =SUM($G$5:G61)/$G$82 -> 0.9932024 | J61: S | L61: Bloco D: OK; 2 alívios + 2 manômetros | M61: Composição própria | N61: Composição 7 (projetista) | O61: Insumo SINAPI 6317 (tê de redução galv. 2½ × 1¼") + mão de obra SINAPI
A62: C | B62: 58 | C62: 13.4 | D62: 261 | E62: Extintor ABC 6 kg | F62: 3 | G62: 802.89 | H62: =G62/$G$82 -> 0.0010310392 | I62: =SUM($G$5:G62)/$G$82 -> 0.99423344 | J62: S → A | K62: -71.4 | L62: Bloco G: NÃO OK só por BDI | M62: Cotação | N62: Print de loja + mão de obra | O62: Extintor R$ 199,99 (cotação); recomendado trocar pela composição ORSE
A63: C | B63: 59 | C63: 8.3.4 | D63: 125 | E63: Cotovelo 45° galvanizado 2½" | F63: 4 | G63: 686.04 | H63: =G63/$G$82 -> 0.00088098508 | I63: =SUM($G$5:G63)/$G$82 -> 0.99511443 | J63: S | L63: Bloco D: conferir no isométrico | M63: SINAPI | N63: 94474 | O63: Igual à tabela SINAPI-PA 06/2025 ao centavo
A64: C | B64: 60 | C64: 8.2.2 | D64: 96 | E64: Tubo PVC DN 25 | F64: 34 m | G64: 584.8 | H64: =G64/$G$82 -> 0.00075097673 | I64: =SUM($G$5:G64)/$G$82 -> 0.9958654 | J64: S | L64: Bloco C: conferir no isométrico | M64: SINAPI | N64: 89402 | O64: Igual à tabela SINAPI-PA 06/2025 ao centavo
A65: C | B65: 61 | C65: 8.2.15 | D65: 109 | E65: Tê PVC DN 60 | F65: 7 | G65: 503.86 | H65: =G65/$G$82 -> 0.00064703683 | I65: =SUM($G$5:G65)/$G$82 -> 0.99651244 | J65: S | L65: Bloco C: conferir no isométrico | M65: SINAPI | N65: 94696 | O65: Igual à tabela SINAPI-PA 06/2025 ao centavo
A66: C | B66: 62 | C66: 8.3.6 | D66: 127 | E66: Luva galvanizada 2½" | F66: 4 | G66: 441.64 | H66: =G66/$G$82 -> 0.0005671364 | I66: =SUM($G$5:G66)/$G$82 -> 0.99707958 | J66: S | L66: Bloco D: conferir no isométrico | M66: SINAPI | N66: 94467 | O66: Igual à tabela SINAPI-PA 06/2025 ao centavo
A67: C | B67: 63 | C67: 10.6 | D67: 210 | E67: Manômetro 4" | F67: 2 | G67: 390.56 | H67: =G67/$G$82 -> 0.00050154151 | I67: =SUM($G$5:G67)/$G$82 -> 0.99758112 | J67: A | L67: Bloco E: NÃO VERIFICÁVEL; faixa de pressão | M67: Cotação | N67: Print de loja | O67: Manômetro, R$ 168,23
A68: C | B68: 64 | C68: 8.2.12 | D68: 106 | E68: Luva PVC DN 110 | F68: 2 | G68: 305.6 | H68: =G68/$G$82 -> 0.00039243928 | I68: =SUM($G$5:G68)/$G$82 -> 0.99797356 | J68: S | L68: Bloco C: conferir no isométrico | M68: SINAPI | N68: 94671 | O68: Igual à tabela SINAPI-PA 06/2025 ao centavo
A69: C | B69: 65 | C69: 8.2.21 | D69: 115 | E69: Adaptador 75 × 2½" | F69: 6 | G69: 261.9 | H69: =G69/$G$82 -> 0.00033632149 | I69: =SUM($G$5:G69)/$G$82 -> 0.99830988 | J69: S | L69: Bloco C: conferir no isométrico | M69: SINAPI | N69: 89613 | O69: Igual à tabela SINAPI-PA 06/2025 ao centavo
A70: C | B70: 66 | C70: 8.2.24 | D70: 118 | E70: Bucha de redução 32 × 25 | F70: 2 | G70: 258.38 | H70: =G70/$G$82 -> 0.00033180124 | I70: =SUM($G$5:G70)/$G$82 -> 0.99864168 | J70: S | L70: Bloco C: NÃO OK; trocar por SINAPI 103953 (R$ 7,62) | M70: Composição própria | N70: Composição 5 (projetista) | O70: Insumo de bucha DN 110 em composição de bucha 32 × 25; a descrição é a do SINAPI 103953 (R$ 7,62)
A71: C | B71: 67 | C71: 13.3 | D71: 260 | E71: Suporte para extintores | F71: 3 | G71: 230.97 | H71: =G71/$G$82 -> 0.00029660242 | I71: =SUM($G$5:G71)/$G$82 -> 0.99893828 | J71: S | L71: Bloco G: ORSE, NÃO VERIFICÁVEL | M71: ORSE | N71: 1512 | O71: Tabela ORSE não disponível
A72: C | B72: 68 | C72: 8.2.22 | D72: 116 | E72: Luva PVC DN 85 | F72: 2 | G72: 172.94 | H72: =G72/$G$82 -> 0.00022208262 | I72: =SUM($G$5:G72)/$G$82 -> 0.99916036 | J72: S | L72: Bloco C: resíduo? | M72: SINAPI | N72: 89614 | O72: Igual à tabela SINAPI-PA 06/2025 ao centavo
A73: C | B73: 69 | C73: 8.2.8 | D73: 102 | E73: Joelho 90° DN 25 | F73: 13 | G73: 148.98 | H73: =G73/$G$82 -> 0.00019131415 | I73: =SUM($G$5:G73)/$G$82 -> 0.99935168 | J73: S | L73: Bloco C: conferir no isométrico | M73: SINAPI | N73: 89408 | O73: Igual à tabela SINAPI-PA 06/2025 ao centavo
A74: C | B74: 70 | C74: 13.1 | D74: 258 | E74: Placa de rota de fuga | F74: 6 | G74: 107.58 | H74: =G74/$G$82 -> 0.00013814993 | I74: =SUM($G$5:G74)/$G$82 -> 0.99948983 | J74: S | L74: Bloco G: ORSE, NÃO VERIFICÁVEL | M74: ORSE | N74: 12895 | O74: Tabela ORSE não disponível
... A76: C | B76: 72 | C76: 8.3.3 | D76: 124 | E76: Bucha galvanizada 1¼ × ½" | F76: 2 | G76: 93.78 | H76: =G76/$G$82 -> 0.00012042852 | I76: =SUM($G$5:G76)/$G$82 -> 0.99973784 | J76: S | L76: Bloco D: OK; 2 manômetros | M76: Composição própria | N76: Composição 6 (projetista) | O76: Insumo SINAPI 768 (bucha galv. 1¼ × ½") + mão de obra SINAPI
A77: C | B77: 73 | C77: 13.2 | D77: 259 | E77: Placa de segurança contra incêndio | F77: 3 | G77: 81.75 | H77: =G77/$G$82 -> 0.00010498007 | I77: =SUM($G$5:G77)/$G$82 -> 0.99984282 | J77: S → A | K77: -7.29 | L77: Bloco G: OK com ressalva; só material; BDI → aquisição | M77: SINAPI | N77: 37556 (insumo) | O77: Igual ao insumo SINAPI-PA 06/2025; só material, sem instalação
A78: C | B78: 74 | C78: 10.12 | D78: 216 | E78: Registro de esfera DN 20 | F78: 2 | G78: 58.16 | H78: =G78/$G$82 -> 7.4686742e-05 | I78: =SUM($G$5:G78)/$G$82 -> 0.99991751 | J78: S | L78: Bloco E: onde entra? | M78: SINAPI | N78: 103047 | O78: Igual à tabela SINAPI-PA 06/2025 ao centavo
A79: C | B79: 75 | C79: 8.2.18 | D79: 112 | E79: União PVC DN 25 | F79: 2 | G79: 39.64 | H79: =G79/$G$82 -> 5.09041e-05 | I79: =SUM($G$5:G79)/$G$82 -> 0.99996841 | J79: S | L79: Bloco C: conferir no isométrico | M79: SINAPI | N79: 89428 | O79: Igual à tabela SINAPI-PA 06/2025 ao centavo
A80: C | B80: 76 | C80: 8.2.1 | D80: 95 | E80: Tubo PVC DN 20 | F80: 1 m | G80: 14.99 | H80: =G80/$G$82 -> 1.9249557e-05 | I80: =SUM($G$5:G80)/$G$82 -> 0.99998766 | J80: S | L80: Bloco C: resíduo? | M80: SINAPI | N80: 89401 | O80: Igual à tabela SINAPI-PA 06/2025 ao centavo
A81: C | B81: 77 | C81: 8.2.7 | D81: 101 | E81: Joelho 90° DN 20 | F81: 1 | G81: 9.61 | H81: =G81/$G$82 -> 1.2340777e-05 | I81: =SUM($G$5:G81)/$G$82 -> 1 | J81: S | L81: Bloco C: resíduo? | M81: SINAPI | N81: 89404 | O81: Igual à tabela SINAPI-PA 06/2025 ao centavo
E82: Total | G82: =SUM(G5:G81) -> 778719.2 | H82: =SUM(H5:H81) -> 1 | K82: =SUM(K5:K81) -> -24955.96
A84: Fora do Δ BDI da tabela: CPRB de 3,6% no BDI de serviço (≈ −R$ 3,6 mil, depende do regime do contrato); registros e retenções 10.9 a 10.17 (−R$ 1.670,23 se o critério mudar para aquisição); correção da quantidade do 12.3.6 (−R$ 1.911,15, à parte).
A85: Fonte dos valores: tabela fornecida pelo usuário (coluna H da aba PLANILHA ORÇAMENTÁRIA). As colunas "% do total" e "% acum." são calculadas por fórmula. Fonte do preço: ver aba Legenda (origem de cada informação).

Sheet Legenda
A1: Legenda (três usos diferentes de letras)
A2: 1. Classe ABC | B2: Ordem de valor. A = até 80% do valor acumulado (inclui o item que cruza 80%); B = de 80% a 95%; C = de 95% a 100%.
A3: 2. Coluna "BDI" | B3: S = BDI de serviço (27,41%); A = BDI de aquisição (16,08%, mero fornecimento de equipamento ou material). "S → A" = a planilha aplicou S, mas o correto é A.
A4: 3. "Bloco A a G" | B4: Bloco do roteiro de verificação: A = comissionamento (1.13, 1.16) · B = içamento (6.1, 6.2) · C = rede PVC (8.2.x) · D = aço galvanizado (8.3.x) · E = equipamentos e válvulas (10.x) · F = PRFV (12.x) · G = incêndio (13.x).
A6: Outras colunas
A7: Item | B7: Número na planilha (com "+" quando duas linhas foram somadas por serem o mesmo objeto de custo).
A8: Linha | B8: Linha na aba PLANILHA ORÇAMENTÁRIA.
A9: R$ c/ BDI | B9: Coluna H da aba PLANILHA ORÇAMENTÁRIA.
A10: % acum. | B10: Percentual acumulado do valor (fórmula).
A11: Δ BDI | B11: Efeito de trocar o BDI aplicado pelo correto (negativo = redução; 12.3.6 usa quantidade 1).
A12: Status | B12: OK · OK com ressalva · NÃO OK (erro comprovado) · NÃO VERIFICÁVEL (falta documento ou fonte).
A13: Regra de agrupamento | B13: Só para a análise; a medição continua por linha. Soma linhas que são o mesmo objeto de custo (decantador + frete; guindaste produtivo + improdutivo; registro DN 60 de mesmo código). Não agrupa acessórios que são bens diferentes nem fretes de conjunto.
A15: Fonte do preço
A16: SINAPI | B16: Preço igual à tabela SINAPI-PA 06/2025 desonerada, ao centavo (verificado na sessão 1). O código foi identificado pelo preço e pela descrição e conferido com a planilha do projetista (mesmo código nas 36 linhas).
A17: SINAPI sem custo | B17: Código SINAPI que a CAIXA não precifica; o custo foi recomposto pelo orçamentista.
A18: SEDOP / ORSE / EMBASA | B18: Tabelas do Pará, de Sergipe e da Bahia. Não estavam disponíveis: preço não conferido. Códigos conferidos na planilha do projetista.
A19: Cotação Biomais | B19: Proposta única do fornecedor de PRFV (grupo 12).
A20: Cotação | B20: Composição própria cujo insumo principal vem de print de loja ou proposta (aba COTAÇÕES INICIAL).
A21: Composição própria | B21: Composição do orçamentista sem banco oficial identificado para o insumo principal.
A23: Cores | B23: Azul claro = classe A · amarelo = classe B · cinza = classe C · laranja nas colunas BDI e Δ BDI = "S → A".

Sheet Comparação projetista
A1: Comparação: planilha analisada (data-base 06/2025) × planilha do projetista (Sanigy, 23/02/2026)
A2: Projetista: arquivo "ORÇAMENTO ETE. BARROS BARRETO maio-2026 - entregue.xls", aba PLANILHA ORÇAMENTÁRIA; bases SINAPI 11/2025 desonerado, ORSE 05/2025, SEDOP 10/2025, SICRO3 07/2025 (nota da linha 324). Valores com BDI.
A4: # | B4: Item | C4: Descrição | D4: Qtd analisada | E4: Qtd projetista | F4: R$ analisada | G4: R$ projetista | H4: Diferença (R$) | I4: Diferença (%) | J4: Linha no projetista | K4: Fonte / código no projetista | L4: Observação
A5: 1 | B5: 12.4.1 + 12.4.2 | C5: Decantador secundário 4,00 × 4,10 m + frete | D5: 2 + 2 | E5: 2 + 2 | F5: 215671.4 | G5: 215671.4 | H5: =F5-G5 -> 0 | I5: =IF(G5=0,"",H5/G5) -> 0 | J5: 264 e 265 | K5: COTAÇÃO - / COTAÇÃO - | L5: Idêntico (mesma proposta Biomais e mesmo BDI de serviço)
A6: 2 | B6: 6.1 + 6.2 | C6: Guindaste 75 t (horas produtivas + improdutivas) | D6: 240 h + 480 h | E6: 240 + 480 | F6: 47892 | G6: 47824.8 | H6: =F6-G6 -> 67.2 | I6: =IF(G6=0,"",H6/G6) -> 0.0014051287 | J6: 66 e 67 | K6: SINAPI 102850 / SINAPI 102851 | L6: Mesmo código sem custo e mesma recomposição (materiais + operador); diferença de R$ 0,22/h nos materiais
A7: 3 | B7: 12.1.3 | C7: Revestimento e reforço interno (UASB) | D7: 2 | E7: 2 | F7: 33609.38 | G7: 33609.38 | H7: =F7-G7 -> 0 | I7: =IF(G7=0,"",H7/G7) -> 0 | J7: 242 | K7: COTAÇÃO - | L7: Idêntico (mesma proposta Biomais e mesmo BDI de serviço)
A8: 4 | B8: 10.4 | C8: Difusor 250 mm | D8: 140 | E8: 140 | F8: 30354.8 | G8: 26196.8 | H8: =F8-G8 -> 4158 | I8: =IF(G8=0,"",H8/G8) -> 0.15872168 | J8: 212 | K8: COTAÇÃO - | L8: Mesmo insumo cotado; a analisada soma mão de obra de instalação, a do projetista é só fornecimento
A9: 5 | B9: 12.1.6 | C9: Montagem do sistema (UASB) | D9: 2 | E9: 2 | F9: 29576.26 | G9: 29576.26 | H9: =F9-G9 -> 0 | I9: =IF(G9=0,"",H9/G9) -> 0 | J9: 245 | K9: COTAÇÃO - | L9: Idêntico (mesma proposta Biomais e mesmo BDI de serviço)
A10: 6 | B10: 12.2.1 | C10: Revestimento e reforço interno (FBAS) | D10: 2 | E10: 2 | F10: 29576.26 | G10: 29576.26 | H10: =F10-G10 -> 0 | I10: =IF(G10=0,"",H10/G10) -> 0 | J10: 249 | K10: COTAÇÃO - | L10: Idêntico (mesma proposta Biomais e mesmo BDI de serviço)
A11: 7 | B11: 12.1.1 | C11: Separador trifásico | D11: 2 | E11: 2 | F11: 25886.62 | G11: 25886.62 | H11: =F11-G11 -> 0 | I11: =IF(G11=0,"",H11/G11) -> 0 | J11: 240 | K11: COTAÇÃO - | L11: Idêntico (mesma proposta Biomais e mesmo BDI de serviço)
A12: 8 | B12: 1.13 | C12: Comissionamento da ETE (EMBASA) | D12: 1 | E12: 1 | F12: 25370.35 | G12: 38386.51 | H12: =F12-G12 -> -13016.16 | I12: =IF(G12=0,"",H12/G12) -> -0.33908162 | J12: 28 | K12: EMBASA 41.05.01 | L12: Mesmo código EMBASA; a analisada está 33,9% abaixo. Pedir as duas composições para explicar a diferença
A13: 9 | B13: 10.3 | C13: Soprador radial duplo estágio | D13: 2 | E13: 2 | F13: 24987.56 | G13: 24534.42 | H13: =F13-G13 -> 453.14 | I13: =IF(G13=0,"",H13/G13) -> 0.018469562 | J13: 211 | K13: COTAÇÃO - | L13: Mesmo insumo cotado; a analisada soma mão de obra de instalação, a do projetista é só fornecimento
A14: 10 | B14: 12.1.2 | C14: Defletor em PRFV | D14: 2 | E14: 2 | F14: 24198.74 | G14: 24198.74 | H14: =F14-G14 -> 0 | I14: =IF(G14=0,"",H14/G14) -> 0 | J14: 241 | K14: COTAÇÃO | L14: Idêntico (mesma proposta Biomais e mesmo BDI de serviço)
A15: 11 | B15: 12.2.4 | C15: Montagem do sistema (FBAS) | D15: 2 | E15: 2 | F15: 24198.74 | G15: 24198.74 | H15: =F15-G15 -> 0 | I15: =IF(G15=0,"",H15/G15) -> 0 | J15: 252 | K15: COTAÇÃO - | L15: Idêntico (mesma proposta Biomais e mesmo BDI de serviço)
A16: 12 | B16: 10.8 | C16: Pall ring 2" | D16: 15 m³ | E16: 15 | F16: 21270.15 | G16: 20546.1 | H16: =F16-G16 -> 724.05 | I16: =IF(G16=0,"",H16/G16) -> 0.035240265 | J16: 216 | K16: COTAÇÃO - | L16: Mesmo insumo cotado; a analisada soma mão de obra de instalação, a do projetista é só fornecimento
... A81: 77 | B81: 8.2.7 | C81: Joelho 90° DN 20 | D81: 1 | E81: 1 | F81: 9.61 | G81: 9.59 | H81: =F81-G81 -> 0.02 | I81: =IF(G81=0,"",H81/G81) -> 0.0020855057 | J81: 100 | K81: SINAPI 89404 | L81: Mesmo código; diferença = data-base do SINAPI (06/2025 na analisada × 11/2025 na do projetista)
C82: Total do escopo mecânico | F82: =SUM(F5:F81) -> 778719.2 | G82: =SUM(G5:G81) -> 786370.57 | H82: =F82-G82 -> -7651.37 | I82: =H82/G82 -> -0.0097299801
A84: Diferença positiva = a planilha analisada está acima da do projetista. Linhas em amarelo: diferenças que não são de data-base nem de mão de obra.
A85: Totais gerais (fora do escopo mecânico): analisada R$ 2.343.873,57 (HANDOFF, seção 3) × projetista R$ 1.892.034,82 (aba RESUMO). A diferença de R$ 451.838,75 está nos grupos não mecânicos e precisa da planilha analisada para ser localizada.
